{"title":"Combined feed","url":"https://MOVIECORD.github.io/broadcast/all.xml","elements":[{"title":"깜빵에서 7년간 익힌 사기술로 완벽하게 복수하는 방법┃리볼버, MBC 220724 방송 (출발! 비디오 여행 모바일 ─ 스페셜영상)","contents":"2022-07-24","link":"https://m.imbc.com/Vod/SketchView/1000827100828100000","retrieved":1659242096138,"image":"https://img.imbc.com/adams/Content/20227/133031877049112853.jpg"},{"title":"잘생긴 애 옆에 재밌는 애! 그게 바로 구교환!  l D.P., MBC 220724 방송 (출발! 비디오 여행 모바일 ─ 스페셜영상)","contents":"2022-07-24","link":"https://m.imbc.com/Vod/SketchView/1000827100827100000","retrieved":1659242096138,"image":"https://img.imbc.com/adams/Content/20227/133031876181598360.jpg"},{"title":"재벌가는 배우자를 이렇게 만나는구나... l 블랙의 신부, MBC 220724 방송 (출발! 비디오 여행 모바일 ─ 스페셜영상)","contents":"2022-07-24","link":"https://m.imbc.com/Vod/SketchView/1000827100826100000","retrieved":1659242096151,"image":"https://img.imbc.com/adams/Content/20227/133031874897041340.jpg"},{"title":"전도연, 송강호, 이병헌, 임시완... 라인업 실화? 이들이 비상선언한 이유는?┃비상선언, MBC 220724 방송 (출발! 비디오 여행 모바일 ─ 스페셜영상)","contents":"2022-07-24","link":"https://m.imbc.com/Vod/SketchView/1000827100825100000","retrieved":1659242096152,"image":"https://img.imbc.com/adams/Content/20227/133031836922674321.jpg"},{"title":"탕웨이의 리즈시절, 놓치지 않을 거예요┃색, 계, MBC 220717 방송 (출발! 비디오 여행 모바일 ─ 스페셜영상)","contents":"2022-07-17","link":"https://m.imbc.com/Vod/SketchView/1000827100824100000","retrieved":1659242096156,"image":"https://img.imbc.com/adams/Content/20227/133025854567127751.jpg"},{"title":"사고 한번 났을 뿐인데, 내가 이렇게 잘생겨졌다고?┃핸썸, MBC 220717 방송 (출발! 비디오 여행 모바일 ─ 스페셜영상)","contents":"2022-07-17","link":"https://m.imbc.com/Vod/SketchView/1000827100823100000","retrieved":1659242096156,"image":"https://img.imbc.com/adams/Content/20227/133025853346803700.jpg"},{"title":"창고에 다녀온 후 엄마가 이상해졌어요..┃뒤틀린 집, MBC 220717 방송 (출발! 비디오 여행 모바일 ─ 스페셜영상)","contents":"2022-07-17","link":"https://m.imbc.com/Vod/SketchView/1000827100822100000","retrieved":1659242096157,"image":"https://img.imbc.com/adams/Content/20227/133025852418800726.jpg"},{"title":"※혈압주의※ 재활용도 안 되는 인간쓰레기 ┃임파서블 러브, MBC 220717 방송 (출발! 비디오 여행 모바일 ─ 스페셜영상)","contents":"2022-07-17","link":"https://m.imbc.com/Vod/SketchView/1000827100821100000","retrieved":1659242096160,"image":"https://img.imbc.com/adams/Content/20227/133025851733796379.jpg"},{"title":"임시완의 표정에 대박을 감지했다┃비상선언, MBC 220717 방송 (출발! 비디오 여행 모바일 ─ 스페셜영상)","contents":"2022-07-17","link":"https://m.imbc.com/Vod/SketchView/1000827100820100000","retrieved":1659242096160,"image":"https://img.imbc.com/adams/Content/20227/133025850826259024.jpg"},{"title":"[소문의 시작] 헌트 / [도도한 영화] 카터 / [존 박의 플레이리스트] 브로커 / [1+1] 더 킬러: 죽어도 되는 아이 + 미씽: 사라진 여자 / [신들의 전쟁] 영화가 좋다 사심 PICK 인물 레포트, '톰 크루즈' 편 (영화가 좋다 ─ 다시보기)","contents":"어제 방송","link":"https://program.kbs.co.kr/2tv/enter/ilovemovie/pc/index.html?source=episode&sname=vod&stype=vod&program_code=T2006-0995&program_id=PS-2022121227-01-000&broadcast_complete_yn=N&local_station_code=00&section_code=04&section_sub_code=02","retrieved":1659152965456,"image":"https://d2fc09gk1936lv.cloudfront.net/kbs/390x219/mediafactory.play.kbs.co.kr/vod/2022/07/30/62e49e6451d48afc04f294aa/thumbnail/62e49e6451d48afc04f294aa_edit_0_1659150713248.jpg"},{"title":"꿀잼 영화가 좋다 - [존 박의 플레이리스트] 미성년 / [도도한 영화] 보통의 용기 (영화가 좋다 ─ 다시보기)","contents":"4일 전 방송","link":"https://program.kbs.co.kr/2tv/enter/ilovemovie/pc/index.html?source=episode&sname=vod&stype=vod&program_code=T2020-0267&program_id=PS-2022120968-01-001&broadcast_complete_yn=N&local_station_code=00&section_code=04&section_sub_code=02","retrieved":1658920643849,"image":"https://d2fc09gk1936lv.cloudfront.net/kbs/390x219/mediafactory.play.kbs.co.kr/vod/2022/07/27/62e110b551d48afc04f24611/thumbnail/62e110b551d48afc04f24611_edit_0_1658917585536.jpg"},{"title":"[요주의 픽] 카터 / [존박의 플레이리스트] 레인 맨 / [소문의 시작] 비상선언 / [도도한 영화] 앰뷸런스 / [영화보고서] 환불 안되는 배우들의 입금 ‘고생’담 BEST 5 / [1+1] 범죄도시2 + 국제수사 (영화가 좋다 ─ 다시보기)","contents":"810회","link":"https://program.kbs.co.kr/2tv/enter/ilovemovie/pc/index.html?source=episode&sname=vod&stype=vod&program_code=T2006-0995&program_id=PS-2022103494-01-000&broadcast_complete_yn=N&local_station_code=00&section_code=04&section_sub_code=02","retrieved":1658547390489,"image":"https://d2fc09gk1936lv.cloudfront.net/kbs/390x219/mediafactory.play.kbs.co.kr/vod/2022/07/23/62db60ac345051f1a12121a5/thumbnail/62db60ac345051f1a12121a5_edit_0_1658545374813.jpg"},{"title":"꿀잼 영화가 좋다 - [도도한 영화] Re-BORN / [소문의 시작] 외계+인 1부 (영화가 좋다 ─ 다시보기)","contents":"141회","link":"https://program.kbs.co.kr/2tv/enter/ilovemovie/pc/index.html?source=episode&sname=vod&stype=vod&program_code=T2020-0267&program_id=PS-2022120967-01-001&broadcast_complete_yn=N&local_station_code=00&section_code=04&section_sub_code=02","retrieved":1658312542785,"image":"https://d2fc09gk1936lv.cloudfront.net/kbs/390x219/mediafactory.play.kbs.co.kr/vod/2022/07/20/62d7d48eb18f9e9a1864e831/thumbnail/62d7d48eb18f9e9a1864e831_edit_0_1658312383692.jpg"},{"title":"[도도한 영화] 보통의 용기 / [요주의 픽] 불릿 트레인 · 신병 / [아찔한 인터뷰] 헌트 / [1+1] 마녀(魔女) Part2. The Other One + 루시 / [요주의 픽] 리미트 / [존 박의 플레이리스트] 미성년 (영화가 좋다 ─ 다시보기)","contents":"809회","link":"https://program.kbs.co.kr/2tv/enter/ilovemovie/pc/index.html?source=episode&sname=vod&stype=vod&program_code=T2006-0995&program_id=PS-2022103493-01-000&broadcast_complete_yn=N&local_station_code=00&section_code=04&section_sub_code=02","retrieved":1657942029705,"image":"https://d2fc09gk1936lv.cloudfront.net/kbs/390x219/mediafactory.play.kbs.co.kr/vod/2022/07/16/62d223f62f9e6dcaabd50a7d/thumbnail/62d223f62f9e6dcaabd50a7d_edit_0_1657939774727.jpg"},{"title":"꿀잼 영화가 좋다 - [소문의 시작] 더 킬러: 죽어도 되는 아이 / [도도한 영화] 아이를 위한 아이 (영화가 좋다 ─ 다시보기)","contents":"140회","link":"https://program.kbs.co.kr/2tv/enter/ilovemovie/pc/index.html?source=episode&sname=vod&stype=vod&program_code=T2020-0267&program_id=PS-2022110502-01-001&broadcast_complete_yn=N&local_station_code=00&section_code=04&section_sub_code=02","retrieved":1657710975194,"image":"https://d2fc09gk1936lv.cloudfront.net/kbs/390x219/mediafactory.play.kbs.co.kr/vod/2022/07/13/62ce9f592f9e6dcaabd4c805/thumbnail/62ce9f592f9e6dcaabd4c805_edit_0_1657709023975.jpg"},{"title":"[요주의 픽] 미니언즈2 / [존박의 플레이리스트] 멘 / [소문의 시작] 외계+인 1부 / [도도한 영화] Re-BORN / [영화보고서] 스타들이 처음 빛났던 순간, 그때 그 시절 베스트 5 / [1+1] 전국노래자랑 + 헬머니 (영화가 좋다 ─ 다시보기)","contents":"808회","link":"https://program.kbs.co.kr/2tv/enter/ilovemovie/pc/index.html?source=episode&sname=vod&stype=vod&program_code=T2006-0995&program_id=PS-2022103491-01-000&broadcast_complete_yn=N&local_station_code=00&section_code=04&section_sub_code=02","retrieved":1657340658159,"image":"https://d2fc09gk1936lv.cloudfront.net/kbs/390x219/mediafactory.play.kbs.co.kr/vod/2022/07/09/62c8f4d8a732184bd0a3796d/thumbnail/62c8f4d8a732184bd0a3796d_edit_0_1657337781517.jpg"},{"title":"꿀잼 영화가 좋다 - [1+1] 핸썸 + 정직한 후보 (영화가 좋다 ─ 다시보기)","contents":"139회","link":"https://program.kbs.co.kr/2tv/enter/ilovemovie/pc/index.html?source=episode&sname=vod&stype=vod&program_code=T2020-0267&program_id=PS-2022110501-01-001&broadcast_complete_yn=N&local_station_code=00&section_code=04&section_sub_code=02","retrieved":1657106276475,"image":"https://d2fc09gk1936lv.cloudfront.net/kbs/390x219/mediafactory.play.kbs.co.kr/vod/2022/07/06/62c562878a7f2922417b2e82/thumbnail/62c562878a7f2922417b2e82_edit_0_1657103494167.jpg"},{"title":"[존 박의 플레이리스트] 안나 / [아찔한 인터뷰] 외계+인 / [소문의 시작] 더 킬러: 죽어도 되는 아이 / [1+1] 비와 당신의 이야기 + 지금 만나러 갑니다 / [도도한 영화] 아이를 위한 아이 (영화가 좋다 ─ 다시보기)","contents":"807회","link":"https://program.kbs.co.kr/2tv/enter/ilovemovie/pc/index.html?source=episode&sname=vod&stype=vod&program_code=T2006-0995&program_id=PS-2022103454-01-000&broadcast_complete_yn=N&local_station_code=00&section_code=04&section_sub_code=02","retrieved":1656733583903,"image":"https://d2fc09gk1936lv.cloudfront.net/kbs/390x219/mediafactory.play.kbs.co.kr/vod/2022/07/02/62bfb08dfa65a4f226673c84/thumbnail/62bfb08dfa65a4f226673c84_edit_0_1656730872585.jpg"}]}